shasha4/Jun.py
shasha4/KimHeeYeon.py
shasha4/KimJuhee.py
shasha4/ParkJiHye.py
shasha4/YangHeeKwon.py
shasha4/Yong.py
shasha4/__init__.py
shasha4-1.0.0.dist-info/LICENSE.txt
shasha4-1.0.0.dist-info/METADATA
shasha4-1.0.0.dist-info/WHEEL
shasha4-1.0.0.dist-info/top_level.txt
shasha4-1.0.0.dist-info/RECORD
