Metadata-Version: 2.1
Name: shasha4
Version: 1.0.0
Summary: For Scraping Naver Finance
Home-page: https://github.com/MoonsRainbow/shasha4.git
Author: MoonsRainbow
Author-email: Moons_Rainbow@kakao.com
License: MoonsRainbow
License-File: LICENSE.txt
Requires-Dist: requests
Requires-Dist: tqdm
Requires-Dist: bs4
Requires-Dist: pandas
Requires-Dist: konlpy
Requires-Dist: wordcloud
Requires-Dist: matplotlib
